uzbstemmer/__init__.py
uzbstemmer-0.4.dist-info/LICENSE.txt
uzbstemmer-0.4.dist-info/METADATA
uzbstemmer-0.4.dist-info/WHEEL
uzbstemmer-0.4.dist-info/top_level.txt
uzbstemmer-0.4.dist-info/RECORD
